agilent34410a/__init__.py
agilent34410a/agilent34410a.py
py34410a_tspspi-0.0.1.dist-info/LICENSE.md
py34410a_tspspi-0.0.1.dist-info/METADATA
py34410a_tspspi-0.0.1.dist-info/WHEEL
py34410a_tspspi-0.0.1.dist-info/top_level.txt
py34410a_tspspi-0.0.1.dist-info/RECORD
