Metadata-Version: 2.1
Name: py34410a-tspspi
Version: 0.0.1
Summary: Unofficial control library for Agilent 34410A multimeter
Home-page: https://github.com/tspspi/py34410a
Author: Thomas Spielauer
Author-email: pypipackages01@tspi.at
Classifier: Programming Language :: Python :: 3
Classifier: License :: OSI Approved :: BSD License
Classifier: Operating System :: OS Independent
Requires-Python: >=3.6
License-File: LICENSE.md
Requires-Dist: pylabdevs-tspspi >=0.0.11
